[
  {
    "name": "ネズミ年",
    "emoji": "🐭",
    "years": "1960, 1972, 1984, 1996, 2008, 2020",
    "content": "今日のネズミ年のあなたは、新しい発見に恵まれる一日となるでしょう。特に人との交流から思わぬヒントやチャンスが舞い込む予感です。積極的に会話を楽しみ、心の扉を開いてみてください。",
    "lucky_numbers": [
      3,
      12,
      25,
      33,
      41,
      7
    ],
    "lucky_color": "ゴールド",
    "advice": "積極的に交流を楽しんでください。"
  },
  {
    "name": "ウシ年",
    "emoji": "🐂",
    "years": "1961, 1973, 1985, 1997, 2009, 2021",
    "content": "ウシ年のあなたは、これまでコツコツと積み重ねてきた努力が報われる日となるでしょう。計画通りに物事が進みやすく、安定した運気に恵まれます。焦らず、自分のペースで着実に進んでください。",
    "lucky_numbers": [
      8,
      17,
      26,
      35,
      42,
      11
    ],
    "lucky_color": "グリーン",
    "advice": "コツコツと取り組む姿勢が成功を呼びます。"
  },
  {
    "name": "トラ年",
    "emoji": "🐅",
    "years": "1962, 1974, 1986, 1998, 2010, 2022",
    "content": "トラ年のあなたにとって、今日は新たな挑戦のチャンスが訪れるでしょう。リーダーシップを発揮する場面があるかもしれません。恐れずに一歩踏み出すことで、素晴らしい成果を手にできます。",
    "lucky_numbers": [
      1,
      10,
      19,
      28,
      37,
      4
    ],
    "lucky_color": "レッド",
    "advice": "恐れずに新しい一歩を踏み出しましょう。"
  },
  {
    "name": "ウサギ年",
    "emoji": "🐇",
    "years": "1963, 1975, 1987, 1999, 2011, 2023",
    "content": "ウサギ年のあなたは、平和で穏やかな一日を過ごせるでしょう。心身ともにリラックスできる時間を持つことが大切です。身近な人との会話や、好きなことに没頭する時間を大切にしてください。",
    "lucky_numbers": [
      2,
      9,
      18,
      27,
      36,
      5
    ],
    "lucky_color": "ピンク",
    "advice": "心身の休息を大切にしてください。"
  },
  {
    "name": "リュウ年",
    "emoji": "🐉",
    "years": "1964, 1976, 1988, 2000, 2012, 2024",
    "content": "リュウ年の今日は、運気が上昇し、あなたのアイデアが光る日となるでしょう。直感を信じて行動することで、良い結果を引き寄せられます。新しい企画や創造的な活動に挑戦するのに最適です。",
    "lucky_numbers": [
      4,
      13,
      22,
      31,
      40,
      10
    ],
    "lucky_color": "パープル",
    "advice": "直感を信じて行動すると良いでしょう。"
  },
  {
    "name": "ヘビ年",
    "emoji": "🐍",
    "years": "1965, 1977, 1989, 2001, 2013, 2025",
    "content": "ヘビ年のあなたは、集中力が高まり、物事を深く探求するのに良い一日です。知識を深めたり、趣味に没頭したりすることで、充実感を得られるでしょう。じっくりと観察することが新たな発見につながります。",
    "lucky_numbers": [
      6,
      15,
      24,
      33,
      42,
      9
    ],
    "lucky_color": "ブラック",
    "advice": "じっくりと物事を観察すると新たな発見があります。"
  },
  {
    "name": "ウマ年",
    "emoji": "🐎",
    "years": "1966, 1978, 1990, 2002, 2014",
    "content": "ウマ年のあなたは、エネルギッシュに活動できる一日となるでしょう。新しい出会いや楽しいイベントに恵まれる予感です。積極的に外に出て、人との交流を楽しむことで運気がさらに高まります。",
    "lucky_numbers": [
      7,
      16,
      25,
      34,
      43,
      1
    ],
    "lucky_color": "オレンジ",
    "advice": "積極的に外に出て、人との交流を楽しんでください。"
  },
  {
    "name": "ヒツジ年",
    "emoji": "🐑",
    "years": "1967, 1979, 1991, 2003, 2015",
    "content": "ヒツジ年の今日は、調和と協力がテーマとなります。周囲の人々と協力し合うことで、物事がスムーズに進むでしょう。心穏やかに過ごすことができ、精神的な充実感を得られます。",
    "lucky_numbers": [
      5,
      14,
      23,
      32,
      39,
      8
    ],
    "lucky_color": "ブルー",
    "advice": "周囲との協力で良い結果が生まれます。"
  },
  {
    "name": "サル年",
    "emoji": "🐒",
    "years": "1968, 1980, 1992, 2004, 2016",
    "content": "サル年のあなたは、ひらめきに満ちた一日を過ごせるでしょう。遊び心を持って物事に取り組むと、思わぬ良いアイデアが浮かびます。柔軟な発想で、新しい可能性を探ってみてください。",
    "lucky_numbers": [
      3,
      12,
      21,
      30,
      39,
      6
    ],
    "lucky_color": "シルバー",
    "advice": "柔軟な発想が新しい道を開きます。"
  },
  {
    "name": "トリ年",
    "emoji": "🐓",
    "years": "1969, 1981, 1993, 2005, 2017",
    "content": "トリ年のあなたは、計画の見直しや整理整頓に良い一日です。身の回りの不要なものを片付けたり、頭の中を整理したりすることで、運気が向上します。クリアな視点で未来を見つめ直しましょう。",
    "lucky_numbers": [
      2,
      11,
      20,
      29,
      38,
      13
    ],
    "lucky_color": "ホワイト",
    "advice": "身の回りを整えることで運気が向上します。"
  },
  {
    "name": "イヌ年",
    "emoji": "🐕",
    "years": "1970, 1982, 1994, 2006, 2018",
    "content": "イヌ年の今日は、信頼関係を深めるのに最適な日です。特に家族や親しい友人との時間を大切にしてください。誠実な態度で接することで、絆がより一層強まるでしょう。感謝の気持ちを伝えることも忘れずに。",
    "lucky_numbers": [
      1,
      10,
      19,
      28,
      37,
      40
    ],
    "lucky_color": "ブラウン",
    "advice": "大切な人との絆を深める良い機会です。"
  },
  {
    "name": "イノシシ年",
    "emoji": "🐗",
    "years": "1971, 1983, 1995, 2007, 2019",
    "content": "イノシシ年のあなたは、充実感を得られる一日となるでしょう。目標達成に向けて努力することで、大きな喜びを感じられます。目の前の課題に全力で取り組むことで、望む結果を引き寄せられます。",
    "lucky_numbers": [
      9,
      18,
      27,
      36,
      43,
      17
    ],
    "lucky_color": "ダークグリーン",
    "advice": "目の前の課題に全力で取り組んでください。"
  }
]