[
  {
    "name": "양자리",
    "name_en": "Aries",
    "emoji": "♈",
    "dates": "3/21-4/19",
    "content": "오늘은 당신의 에너지가 최고조에 달하는 날입니다. 새로운 도전을 두려워하지 말고, 미뤄왔던 일을 과감하게 시작해보세요. 주변 사람들과의 협력이 큰 성공을 가져올 수 있습니다.",
    "lucky_numbers": [
      3,
      12,
      25,
      33,
      41,
      7
    ],
    "lucky_color": "골드",
    "advice": "자신감을 가지고 당신의 아이디어를 적극적으로 표현하세요."
  },
  {
    "name": "황소자리",
    "name_en": "Taurus",
    "emoji": "♉",
    "dates": "4/20-5/20",
    "content": "안정과 편안함을 추구하는 당신에게 휴식이 필요한 하루입니다. 복잡한 생각은 잠시 미루고, 좋아하는 취미나 활동에 몰두하며 재충전의 시간을 가지세요. 뜻밖의 행운이 찾아올 수 있습니다.",
    "lucky_numbers": [
      2,
      11,
      22,
      30,
      39,
      45
    ],
    "lucky_color": "에메랄드 그린",
    "advice": "서두르지 말고, 당신의 속도에 맞춰 천천히 나아가세요."
  },
  {
    "name": "쌍둥이자리",
    "name_en": "Gemini",
    "emoji": "♊",
    "dates": "5/21-6/20",
    "content": "사회적인 교류가 활발해지는 날입니다. 새로운 사람들과의 만남이 당신에게 신선한 영감을 줄 것입니다. 열린 마음으로 대화에 참여하면 좋은 기회를 발견할 수 있습니다.",
    "lucky_numbers": [
      5,
      14,
      19,
      28,
      37,
      42
    ],
    "lucky_color": "스카이 블루",
    "advice": "다양한 의견에 귀 기울이고 당신의 생각을 자유롭게 나누세요."
  },
  {
    "name": "게자리",
    "name_en": "Cancer",
    "emoji": "♋",
    "dates": "6/21-7/22",
    "content": "가정과 내면의 평화가 중요한 하루입니다. 사랑하는 사람들과 함께 시간을 보내며 따뜻한 유대감을 형성하세요. 당신의 직감을 믿고 중요한 결정을 내리는 데 활용해 보세요.",
    "lucky_numbers": [
      4,
      13,
      23,
      31,
      40,
      44
    ],
    "lucky_color": "실버",
    "advice": "당신의 감정에 솔직하고 소중한 사람들에게 마음을 표현하세요."
  },
  {
    "name": "사자자리",
    "name_en": "Leo",
    "emoji": "♌",
    "dates": "7/23-8/22",
    "content": "당신의 리더십과 창의성이 빛나는 날입니다. 주변의 시선을 의식하지 말고, 당신이 가진 재능을 마음껏 펼치세요. 긍정적인 에너지가 주변 사람들에게도 좋은 영향을 미칠 것입니다.",
    "lucky_numbers": [
      1,
      10,
      20,
      29,
      38,
      43
    ],
    "lucky_color": "오렌지",
    "advice": "당신의 열정을 따르고 자신감 있게 행동하세요."
  },
  {
    "name": "처녀자리",
    "name_en": "Virgo",
    "emoji": "♍",
    "dates": "8/23-9/22",
    "content": "세심한 계획과 분석이 필요한 하루입니다. 중요한 업무나 프로젝트가 있다면 꼼꼼하게 검토하고 정리하는 시간을 가지세요. 작은 디테일이 큰 성공을 가져올 수 있습니다.",
    "lucky_numbers": [
      6,
      15,
      24,
      32,
      34,
      4
    ],
    "lucky_color": "네이비",
    "advice": "체계적인 접근 방식으로 당신의 목표를 달성하세요."
  },
  {
    "name": "천칭자리",
    "name_en": "Libra",
    "emoji": "♎",
    "dates": "9/23-10/22",
    "content": "조화와 균형이 중요한 날입니다. 인간관계에서 발생할 수 있는 갈등을 지혜롭게 해결하고, 공정한 판단을 내리세요. 아름다운 것을 가까이하며 마음의 평화를 찾으세요.",
    "lucky_numbers": [
      7,
      16,
      26,
      35,
      21,
      9
    ],
    "lucky_color": "핑크",
    "advice": "모든 면에서 균형을 유지하려 노력하고 타협점을 찾으세요."
  },
  {
    "name": "전갈자리",
    "name_en": "Scorpio",
    "emoji": "♏",
    "dates": "10/23-11/21",
    "content": "깊은 통찰력으로 숨겨진 진실을 발견할 수 있는 날입니다. 중요한 결정을 앞두고 있다면 당신의 직감을 믿고 내면의 목소리에 귀 기울이세요. 변화를 두려워하지 말고 받아들이세요.",
    "lucky_numbers": [
      8,
      17,
      27,
      36,
      45,
      1
    ],
    "lucky_color": "버건디",
    "advice": "당신의 강한 의지로 목표를 향해 나아가세요."
  },
  {
    "name": "사수자리",
    "name_en": "Sagittarius",
    "emoji": "♐",
    "dates": "11/22-12/21",
    "content": "새로운 경험과 모험을 갈망하는 당신에게 좋은 기회가 찾아올 것입니다. 여행 계획을 세우거나 새로운 분야를 탐험해 보세요. 긍정적인 태도가 행운을 불러올 것입니다.",
    "lucky_numbers": [
      9,
      18,
      28,
      37,
      40,
      2
    ],
    "lucky_color": "퍼플",
    "advice": "개방적인 마음으로 새로운 가능성을 탐색하세요."
  },
  {
    "name": "염소자리",
    "name_en": "Capricorn",
    "emoji": "♑",
    "dates": "12/22-1/19",
    "content": "당신의 인내와 노력이 결실을 맺는 시기입니다. 목표를 향해 꾸준히 나아간다면 예상치 못한 성과를 얻을 수 있습니다. 현실적인 계획을 세우고 실행에 옮기세요.",
    "lucky_numbers": [
      10,
      19,
      29,
      38,
      41,
      5
    ],
    "lucky_color": "다크 그린",
    "advice": "끈기와 성실함으로 당신의 목표를 이루세요."
  },
  {
    "name": "물병자리",
    "name_en": "Aquarius",
    "emoji": "♒",
    "dates": "1/20-2/18",
    "content": "혁신적인 아이디어가 샘솟는 날입니다. 고정관념에서 벗어나 새로운 시각으로 문제를 바라보세요. 당신의 독창적인 생각이 주변에 긍정적인 영향을 미칠 것입니다.",
    "lucky_numbers": [
      11,
      20,
      30,
      39,
      42,
      6
    ],
    "lucky_color": "일렉트릭 블루",
    "advice": "당신의 독특한 개성을 존중하고 자유롭게 표현하세요."
  },
  {
    "name": "물고기자리",
    "name_en": "Pisces",
    "emoji": "♓",
    "dates": "2/19-3/20",
    "content": "당신의 예술적 감각과 직관이 풍부해지는 날입니다. 명상이나 창작 활동을 통해 내면의 평화를 찾으세요. 주변 사람들에게 따뜻한 위로와 공감을 전하면 좋은 관계를 형성할 수 있습니다.",
    "lucky_numbers": [
      12,
      21,
      31,
      40,
      43,
      8
    ],
    "lucky_color": "아쿠아마린",
    "advice": "당신의 직감을 믿고 타인에게 연민을 보여주세요."
  }
]