[
  {
    "name": "양자리",
    "name_en": "Aries",
    "emoji": "♈",
    "dates": "3/21-4/19",
    "content": "오늘은 당신의 내면에 숨겨진 강한 추진력이 빛을 발하는 날입니다. 새로운 아이디어나 계획이 있다면 주저하지 말고 실행에 옮겨보세요. 당신의 리더십이 주변 사람들에게 긍정적인 영향을 미칠 것입니다.",
    "lucky_numbers": [
      3,
      12,
      25,
      33,
      41,
      7
    ],
    "lucky_color": "레드",
    "advice": "용기를 가지고 새로운 도전을 시작하세요."
  },
  {
    "name": "황소자리",
    "name_en": "Taurus",
    "emoji": "♉",
    "dates": "4/20-5/20",
    "content": "재정적인 안정과 실질적인 성과에 집중하기 좋은 하루입니다. 꾸준함이 중요한 시기이니, 목표를 향해 묵묵히 나아가세요. 주변 사람들과의 관계에서도 신뢰를 쌓는 것이 중요합니다.",
    "lucky_numbers": [
      2,
      9,
      16,
      23,
      30,
      37
    ],
    "lucky_color": "그린",
    "advice": "당신의 가치를 믿고 현실적인 목표를 세우세요."
  },
  {
    "name": "쌍둥이자리",
    "name_en": "Gemini",
    "emoji": "♊",
    "dates": "5/21-6/20",
    "content": "활발한 의사소통과 새로운 정보 습득이 당신에게 행운을 가져다줄 것입니다. 다양한 사람들과 교류하며 흥미로운 대화를 나눠보세요. 예상치 못한 곳에서 좋은 기회를 발견할 수도 있습니다.",
    "lucky_numbers": [
      5,
      14,
      21,
      29,
      38,
      45
    ],
    "lucky_color": "옐로우",
    "advice": "열린 마음으로 새로운 지식을 받아들이세요."
  },
  {
    "name": "게자리",
    "name_en": "Cancer",
    "emoji": "♋",
    "dates": "6/21-7/22",
    "content": "가족과 가정의 소중함을 느끼고 내면의 평화를 찾는 하루가 될 것입니다. 감성적인 교류가 당신의 마음을 풍요롭게 할 테니, 소중한 사람들과 시간을 보내세요. 직업적인 면에서도 안정감을 추구하는 것이 좋습니다.",
    "lucky_numbers": [
      6,
      15,
      22,
      31,
      39,
      4
    ],
    "lucky_color": "실버",
    "advice": "사랑하는 사람들과 함께 행복을 나누세요."
  },
  {
    "name": "사자자리",
    "name_en": "Leo",
    "emoji": "♌",
    "dates": "7/23-8/22",
    "content": "창의적인 에너지와 자신감이 넘쳐흐르는 날입니다. 당신의 재능을 마음껏 발휘하고 주변의 인정을 받으세요. 새로운 취미를 시작하거나 주목받는 자리에 참여하는 것도 좋습니다.",
    "lucky_numbers": [
      1,
      10,
      17,
      26,
      34,
      42
    ],
    "lucky_color": "골드",
    "advice": "당신의 빛나는 매력을 마음껏 보여주세요."
  },
  {
    "name": "처녀자리",
    "name_en": "Virgo",
    "emoji": "♍",
    "dates": "8/23-9/22",
    "content": "세심한 분석력과 실용적인 접근 방식이 빛을 발하는 하루입니다. 미뤄왔던 일들을 체계적으로 정리하고 건강 관리에 신경 쓰세요. 당신의 꼼꼼함이 큰 성과를 가져다줄 것입니다.",
    "lucky_numbers": [
      8,
      13,
      20,
      27,
      35,
      43
    ],
    "lucky_color": "네이비",
    "advice": "효율적인 계획으로 하루를 알차게 보내세요."
  },
  {
    "name": "천칭자리",
    "name_en": "Libra",
    "emoji": "♎",
    "dates": "9/23-10/22",
    "content": "인간관계와 파트너십에 중요한 의미를 두는 날입니다. 주변 사람들과의 조화를 추구하고 협력적인 자세를 유지하세요. 새로운 만남이 당신에게 긍정적인 변화를 가져올 수 있습니다.",
    "lucky_numbers": [
      11,
      19,
      24,
      32,
      40,
      28
    ],
    "lucky_color": "핑크",
    "advice": "모든 관계에서 균형과 조화를 추구하세요."
  },
  {
    "name": "전갈자리",
    "name_en": "Scorpio",
    "emoji": "♏",
    "dates": "10/23-11/21",
    "content": "내면의 깊은 통찰력과 변화를 모색하기 좋은 하루입니다. 숨겨진 재능을 발견하거나 오랫동안 품어왔던 목표를 향해 나아가기에 적합합니다. 용기를 가지고 변화를 받아들이세요.",
    "lucky_numbers": [
      1,
      7,
      14,
      21,
      28,
      35
    ],
    "lucky_color": "블랙",
    "advice": "내면의 힘을 믿고 과감히 나아가세요."
  },
  {
    "name": "사수자리",
    "name_en": "Sagittarius",
    "emoji": "♐",
    "dates": "11/22-12/21",
    "content": "모험심과 자유로운 영혼이 샘솟는 날입니다. 새로운 경험을 찾아 떠나거나 지적인 탐구를 통해 시야를 넓혀보세요. 긍정적인 태도가 당신을 새로운 기회로 이끌 것입니다.",
    "lucky_numbers": [
      9,
      18,
      27,
      36,
      45,
      6
    ],
    "lucky_color": "퍼플",
    "advice": "새로운 지식과 경험을 탐색하며 성장하세요."
  },
  {
    "name": "염소자리",
    "name_en": "Capricorn",
    "emoji": "♑",
    "dates": "12/22-1/19",
    "content": "목표 달성과 책임감이 강조되는 하루입니다. 꾸준한 노력으로 성과를 이루어낼 수 있으니, 장기적인 계획을 세우고 실천하는 데 집중하세요. 당신의 인내가 결실을 맺을 것입니다.",
    "lucky_numbers": [
      10,
      19,
      28,
      37,
      4,
      13
    ],
    "lucky_color": "브라운",
    "advice": "인내심을 가지고 꾸준히 노력하세요."
  },
  {
    "name": "물병자리",
    "name_en": "Aquarius",
    "emoji": "♒",
    "dates": "1/20-2/18",
    "content": "혁신적인 아이디어와 사회적인 활동이 두드러지는 날입니다. 친구들과 교류하며 새로운 영감을 얻고, 당신의 독창적인 생각을 공유해보세요. 미래 지향적인 태도가 당신에게 행운을 가져다줄 것입니다.",
    "lucky_numbers": [
      11,
      20,
      29,
      38,
      5,
      14
    ],
    "lucky_color": "스카이블루",
    "advice": "당신의 독창적인 아이디어를 자유롭게 펼치세요."
  },
  {
    "name": "물고기자리",
    "name_en": "Pisces",
    "emoji": "♓",
    "dates": "2/19-3/20",
    "content": "직관력과 감수성이 풍부해지는 하루입니다. 내면의 목소리에 귀 기울이고 명상이나 예술 활동을 통해 에너지를 충전하세요. 타인을 돕는 마음이 당신에게 큰 만족감을 줄 것입니다.",
    "lucky_numbers": [
      12,
      21,
      30,
      39,
      6,
      15
    ],
    "lucky_color": "아쿠아마린",
    "advice": "당신의 직관을 믿고 평화로운 시간을 가지세요."
  }
]